margo_parser/__init__.py
margo_parser/exceptions.py
margo_parser/api/__init__.py
margo_parser/api/classes/MargoAssignment.py
margo_parser/api/classes/MargoBlock.py
margo_parser/api/classes/MargoDirective.py
margo_parser/api/classes/MargoMarkdownCellPrambleBlock.py
margo_parser/api/classes/MargoPythonCellPreambleBlock.py
margo_parser/api/classes/MargoStatement.py
margo_parser/api/classes/__init__.py
margo_parser/api/utils/__init__.py
margo_parser/api/utils/get_preamble_block.py
margo_parser/api/utils/get_preamble_source.py
margo_parser/tokenizer/__init__.py
margo_parser/tokenizer/margo.lark
margo_parser/tokenizer/margo_transformer.py
margo_parser/tokenizer/tokenizer.py
margo_parser-1.0.3.dist-info/METADATA
margo_parser-1.0.3.dist-info/WHEEL
margo_parser-1.0.3.dist-info/RECORD
