Metadata-Version: 2.1
Name: margo-parser
Version: 1.0.3
Summary: A notebook description language parser
Project-URL: Homepage, https://github.com/margo-notebooks/margo-parser-py
Project-URL: Bug Tracker, https://github.com/margo-notebooks/margo-parser-py/issues
Author-email: Jake Kara <jake@jakekara.com>
Classifier: License :: OSI Approved :: GNU General Public License v3 (GPLv3)
Classifier: Operating System :: OS Independent
Classifier: Programming Language :: Python :: 3
Requires-Python: >=3.6
Requires-Dist: lark[regex]==1.1.5
Requires-Dist: pyyaml==5.3.1
